what3chars/__init__.py
what3chars/what3chars.py
what3chars-1.0.1.dist-info/LICENSE.txt
what3chars-1.0.1.dist-info/METADATA
what3chars-1.0.1.dist-info/WHEEL
what3chars-1.0.1.dist-info/top_level.txt
what3chars-1.0.1.dist-info/RECORD
